minio_sync_tool/__init__.py
minio_sync_tool/cli.py
minio_sync_tool/minio_helper.py
minio_sync_tool/utils.py
minio_sync_tool/tasks/__init__.py
minio_sync_tool/tasks/sync_repo.py
minio_sync_tool-0.1.0.dist-info/METADATA
minio_sync_tool-0.1.0.dist-info/WHEEL
minio_sync_tool-0.1.0.dist-info/entry_points.txt
minio_sync_tool-0.1.0.dist-info/top_level.txt
minio_sync_tool-0.1.0.dist-info/RECORD
