Metadata-Version: 2.1
Name: minio_sync_tool
Version: 0.1.0
Summary: A package for synchronizing and uploading repositories with MinIO.
Home-page: https://zalogit2.zing.vn/nlp/kilm/ai-platform/minio-sync-tool
Author: Nguyen Tran Trung
Author-email: trungnt17@vng.com.vn
Classifier: Programming Language :: Python :: 3
Classifier: License :: OSI Approved :: MIT License
Classifier: Operating System :: OS Independent
Requires-Python: >=3.6
Requires-Dist: minio
Requires-Dist: tqdm
